LICENSE
statsapiclient/__init__.py
statsapiclient/constants.py
statsapiclient/franchises.py
statsapiclient/games.py
statsapiclient/line_score.py
statsapiclient/plays.py
statsapiclient/schedule.py
statsapiclient/shifts/__init__.py
statsapiclient/shifts/parser.py
statsapiclient/teams.py
statsapiclient/utils.py
statsapiclient-0.2.1.dist-info/LICENSE
statsapiclient-0.2.1.dist-info/WHEEL
statsapiclient-0.2.1.dist-info/METADATA
statsapiclient-0.2.1.dist-info/RECORD
