Metadata-Version: 2.1
Name: statsapiclient
Version: 0.2.1
Summary: A wrapper around the NHL’s JSON API.
Home-page: https://github.com/bplabombarda/statsapiclient
License: MPL-2.0
Keywords: nhl,hockey
Author: Brett LaBombarda
Author-email: bplabombarda@gmail.com
Requires-Python: >=3.8,<4.0
Classifier: Environment :: Console
Classifier: License :: OSI Approved
Classifier: License :: OSI Approved :: Mozilla Public License 2.0 (MPL 2.0)
Classifier: Programming Language :: Python :: 3
Classifier: Programming Language :: Python :: 3.7
Classifier: Programming Language :: Python :: 3.8
Classifier: Programming Language :: Python :: 3.9
Classifier: Topic :: Software Development
Classifier: Topic :: Software Development :: Libraries
Classifier: Topic :: Software Development :: Libraries :: Python Modules
Requires-Dist: beautifulsoup4 (>=4.8.2,<5.0.0)
Requires-Dist: requests (>=2.22,<3.0)
Project-URL: Documentation, https://github.com/bplabombarda/statsapiclient#README.md
Project-URL: Repository, https://github.com/bplabombarda/statsapiclient
